glscpc/__init__.py
glscpc/__main__.py
glscpc/_version.py
glscpc-0.4.0.dist-info/METADATA
glscpc-0.4.0.dist-info/WHEEL
glscpc-0.4.0.dist-info/entry_points.txt
glscpc-0.4.0.dist-info/licenses/LICENSE
glscpc-0.4.0.dist-info/RECORD
