Metadata-Version: 2.1
Name: glscpc
Version: 0.4.0
Summary: GitLab CI ShellCheck pre-commit hook
Author-email: Dries Kennes <dries.kennes@qteal.com>
License: MIT License
License-File: LICENSE
Requires-Python: >=3.8
Requires-Dist: click~=8.1
Requires-Dist: ruamel-yaml~=0.17.32
Requires-Dist: strenum~=0.4.15; python_version < '3.11'
Provides-Extra: shellcheck
Requires-Dist: shellcheck-py; extra == 'shellcheck'
